CHANGES.md
MANIFEST.in
README.rst
setup.py
django_sslify_admin.egg-info/PKG-INFO
django_sslify_admin.egg-info/SOURCES.txt
django_sslify_admin.egg-info/dependency_links.txt
django_sslify_admin.egg-info/not-zip-safe
django_sslify_admin.egg-info/requires.txt
django_sslify_admin.egg-info/top_level.txt
sslifyadmin/__init__.py
sslifyadmin/middleware.py
sslifyadmin/models.py